Metadata-Version: 2.1
Name: xpdacq
Version: 1.1.4
Summary: acquisition module
Home-page: https://github.com/xpdAcq/xpdacq
Author: Songsheng Tao
Author-email: st3107@columbia.edu
License: UNKNOWN
Platform: UNKNOWN
License-File: LICENSE
License-File: AUTHORS.txt
